pyzitadelle/__init__.py
pyzitadelle/coverage.py
pyzitadelle/debug/__init__.py
pyzitadelle/debug/measurement.py
pyzitadelle/exceptions.py
pyzitadelle/fixtures.py
pyzitadelle/reporter.py
pyzitadelle/sessions.py
pyzitadelle/standard.py
pyzitadelle/test_case.py
pyzitadelle/utils.py
pyzitadelle-0.1.1.dist-info/LICENSE
pyzitadelle-0.1.1.dist-info/METADATA
pyzitadelle-0.1.1.dist-info/WHEEL
pyzitadelle-0.1.1.dist-info/RECORD
