Metadata-Version: 2.1
Name: pyzitadelle
Version: 0.1.1
Summary: Pyzitadelle is a quick asynchronous framework for testing python applications
License: GNU LGPL 2.1
Author: alexeev-prog
Author-email: alexeev.dev@mail.ru
Requires-Python: >=3.9,<4.0
Classifier: License :: Other/Proprietary License
Classifier: Programming Language :: Python :: 3
Classifier: Programming Language :: Python :: 3.9
Classifier: Programming Language :: Python :: 3.10
Classifier: Programming Language :: Python :: 3.11
Classifier: Programming Language :: Python :: 3.12
Classifier: Programming Language :: Python :: 3.13
Requires-Dist: asyncio (>=3.4.3,<4.0.0)
Requires-Dist: click (>=8.1.8,<9.0.0)
Requires-Dist: requests (>=2.32.3,<3.0.0)
Requires-Dist: rich (>=13.9.4,<14.0.0)
